{
  "main": {
    "id": "c69f26328fde546a",
    "type": "split",
    "children": [
      {
        "id": "ffc16fc042cffa73",
        "type": "tabs",
        "children": [
          {
            "id": "9624691f1160547a",
            "type": "leaf",
            "state": {
              "type": "graph",
              "state": {}
            }
          },
          {
            "id": "6aea045bbe2433db",
            "type": "leaf",
            "state": {
              "type": "markdown",
              "state": {
                "file": "5. TypeScript/0. Вопросы к собеседованию/Что такое TypeScript. Как настроить проект.md",
                "mode": "preview",
                "source": false
              }
            }
          }
        ]
      }
    ],
    "direction": "vertical"
  },
  "left": {
    "id": "3c7c9be532992e4b",
    "type": "split",
    "children": [
      {
        "id": "e3a85997b8765760",
        "type": "tabs",
        "children": [
          {
            "id": "2b9eca97f11fd816",
            "type": "leaf",
            "state": {
              "type": "file-explorer",
              "state": {
                "sortOrder": "alphabetical"
              }
            }
          },
          {
            "id": "727a8f297f16c7a8",
            "type": "leaf",
            "state": {
              "type": "search",
              "state": {
                "query": "tag:#declare",
                "matchingCase": false,
                "explainSearch": false,
                "collapseAll": false,
                "extraContext": false,
                "sortOrder": "alphabetical"
              }
            }
          },
          {
            "id": "717e92aee162492d",
            "type": "leaf",
            "state": {
              "type": "bookmarks",
              "state": {}
            }
          }
        ]
      }
    ],
    "direction": "horizontal",
    "width": 449.5
  },
  "right": {
    "id": "58407df49daf5547",
    "type": "split",
    "children": [
      {
        "id": "013f564fc2672fbe",
        "type": "tabs",
        "children": [
          {
            "id": "bc30b558a85817c7",
            "type": "leaf",
            "state": {
              "type": "backlink",
              "state": {
                "collapseAll": true,
                "extraContext": true,
                "sortOrder": "alphabetical",
                "showSearch": false,
                "searchQuery": "",
                "backlinkCollapsed": false,
                "unlinkedCollapsed": false
              }
            }
          },
          {
            "id": "fb45945aec97379b",
            "type": "leaf",
            "state": {
              "type": "outgoing-link",
              "state": {
                "linksCollapsed": false,
                "unlinkedCollapsed": false
              }
            }
          },
          {
            "id": "9f6e7a60b6c080c2",
            "type": "leaf",
            "state": {
              "type": "tag",
              "state": {
                "sortOrder": "frequency",
                "useHierarchy": false
              }
            }
          },
          {
            "id": "74670d5ff67feb55",
            "type": "leaf",
            "state": {
              "type": "outline",
              "state": {}
            }
          },
          {
            "id": "d75c6efea73e5c1f",
            "type": "leaf",
            "state": {
              "type": "calendar",
              "state": {}
            }
          }
        ],
        "currentTab": 3
      }
    ],
    "direction": "horizontal",
    "width": 342.5
  },
  "left-ribbon": {
    "hiddenItems": {
      "audio-recorder:Начать/остановить запись": false,
      "graph:Граф": false,
      "switcher:Меню быстрого перехода": false,
      "templates:Вставить шаблон": false,
      "daily-notes:Сегодняшняя заметка": false,
      "command-palette:Открыть палитру команд": false,
      "zk-prefixer:Создать заметку с уникальным идентификатором": false
    }
  },
  "active": "9624691f1160547a",
  "lastOpenFiles": [
    "0. Подготовка к собеседованию/5. TypeScript.md",
    "5. TypeScript/0. Вопросы к собеседованию/Как вы отлавливаете ошибки в TypeScript коде.md",
    "5. TypeScript/0. Вопросы к собеседованию/Разница между типами `void`, `never` и `unknown`.md",
    "5. TypeScript/0. Вопросы к собеседованию/Для чего в TypeScript используют ключевое слово `declare`.md",
    "5. TypeScript/0. Вопросы к собеседованию/Можно ли использовать TypeScript в серверной разработке.md",
    "5. TypeScript/0. Вопросы к собеседованию/Что такое `.map` файл, как и зачем его использовать.md",
    "5. TypeScript/0. Вопросы к собеседованию/Какие области видимости доступны в TypeScript.md",
    "5. TypeScript/0. Вопросы к собеседованию/Что такое общие типы (`generic`) в TypeScript.md",
    "5. TypeScript/0. Вопросы к собеседованию/Разница между типами “Объединение” и “Пересечение”.md",
    "5. TypeScript/0. Вопросы к собеседованию/Для чего в TypeScript используется `NoImplicitAny`.md",
    "5. TypeScript/0. Вопросы к собеседованию/Что такое перечисление (`enum`).md",
    "5. TypeScript/0. Вопросы к собеседованию/Как TypeScript поддерживает необязательные и дефолтные параметры в функции.md",
    "5. TypeScript/0. Вопросы к собеседованию/Разница между внутренним (Internal Module) и внешним модулями (External Module).md",
    "5. TypeScript/0. Вопросы к собеседованию/Модификаторы доступа в TypeScript.md",
    "5. TypeScript/0. Вопросы к собеседованию/Какие элементы ООП поддерживаются в TypeScript.md",
    "5. TypeScript/0. Вопросы к собеседованию/Разница между абстрактным классом (abstract class) и интерфейсом (interface).md",
    "5. TypeScript/0. Вопросы к собеседованию/Что такое внешние объявления переменных (ambient declaration).md",
    "5. TypeScript/0. Вопросы к собеседованию/Что такое директивы с тремя наклонными чертами (Triple-Slash Directives), их типы.md",
    "5. TypeScript/0. Вопросы к собеседованию/Что такое JSX в TypeScript. Какие режимы JSX поддерживает TypeScript.md",
    "5. TypeScript/0. Вопросы к собеседованию/Разница между типом (`type`) и интерфейсом (`interface`).md",
    "5. TypeScript/0. Вопросы к собеседованию/Поддерживает ли TypeScript перегрузку функций.md",
    "5. TypeScript/0. Вопросы к собеседованию/Что такое декораторы.md",
    "5. TypeScript/0. Вопросы к собеседованию/Типы в TypeScript.md",
    "5. TypeScript/0. Вопросы к собеседованию/Плюсы использования TypeScript.md",
    "5. TypeScript/0. Вопросы к собеседованию/Минусы использования TypeScript.md",
    "5. TypeScript/0. Вопросы к собеседованию/Особенности TypeScript.md",
    "5. TypeScript/typescript. Часть 1/2.2 Использование своих типов данных",
    "5. TypeScript/typescript. Часть 1/2.1 Описание типов данных",
    "5. TypeScript/typescript. Часть 1/1. Внутреннее устройство typescript",
    "5. TypeScript/typescript. Часть 2",
    "5. TypeScript/typescript. Часть 1",
    "img/js vs ts.png",
    "2. CSS/Фреймворк",
    "9. Тестирование/Vitest",
    "0. Browser/API/Kubernetes",
    "9. Тестирование/Puppeteer/Puppeteer. Основные понятия",
    "9. Тестирование/Puppeteer",
    "img/Pasted image 20230526111719.png",
    "img/Pasted image 20230526111605.png",
    "sidian/plugi.obns/obsidian-icon-folder/icons/simple-icons/Zyte.svg",
    "sidian/plugi.obns/obsidian-icon-folder/icons/simple-icons/Zwave.svg",
    "sidian/plugi.obns/obsidian-icon-folder/icons/simple-icons/Zulip.svg",
    "sidian/plugi.obns/obsidian-icon-folder/icons/simple-icons/Zotero.svg",
    "sidian/plugi.obns/obsidian-icon-folder/icons/simple-icons/Zorin.svg",
    "sidian/plugi.obns/obsidian-icon-folder/icons/simple-icons/Zoom.svg",
    "sidian/plugi.obns/obsidian-icon-folder/icons/simple-icons/Zomato.svg",
    "Без названия.canvas",
    "0.4 Вопросы к ревью React/Преимущества и недостатки HOC.canvas",
    "Без названия (2).canvas",
    "РАЗБОР СОДЕРЖИМОГО/Область видимости.canvas"
  ]
}